lonny_aws_bin/__init__.py
lonny_aws_bin-0.1.0.dist-info/entry_points.txt
lonny_aws_bin-0.1.0.dist-info/WHEEL
lonny_aws_bin-0.1.0.dist-info/METADATA
lonny_aws_bin-0.1.0.dist-info/RECORD
