Metadata-Version: 2.1
Name: lonny-aws-bin
Version: 0.1.0
Summary: 
Author: None
Requires-Python: >=3.8,<4.0
Classifier: Programming Language :: Python :: 3
Classifier: Programming Language :: Python :: 3.8
Requires-Dist: boto3 (>=1.14.16,<2.0.0)
